pytermfx/__init__.py
pytermfx/color.py
pytermfx/constants.py
pytermfx/escapes.py
pytermfx/keys.py
pytermfx/md.py
pytermfx/style.py
pytermfx/terminal.py
pytermfx/tools.py
pytermfx-0.4.3.dist-info/DESCRIPTION.rst
pytermfx-0.4.3.dist-info/METADATA
pytermfx-0.4.3.dist-info/RECORD
pytermfx-0.4.3.dist-info/WHEEL
pytermfx-0.4.3.dist-info/metadata.json
pytermfx-0.4.3.dist-info/top_level.txt
