Metadata-Version: 2.0
Name: pytermfx
Version: 0.4.3
Summary: Terminal interaction and formatting for Python without curses
Home-page: https://github.com/loganzartman/pytermfx
Author: Logan Zartman
Author-email: logan.zartman@utexas.edu
License: UNKNOWN
Keywords: curses,terminal,colors,ansi,escapes
Platform: UNKNOWN
Classifier: Development Status :: 3 - Alpha
Classifier: License :: OSI Approved :: MIT License
Classifier: Programming Language :: Python :: 3
Requires-Python: >=3
